rtl/parametric_relu.v
// ================================================================================
// Module: Parametric ReLU Activation Function
// Description: This module implements the Parametric ReLU (PReLU) activation
//              function. It takes a fixed-point input and applies the PReLU
//              activation, which allows for a learnable slope for negative inputs.
//              The output is also in fixed-point format.
//              For fixed leaky ReLU, set the slope parameter to a constant
//              value. (in controller)
// --------------------------------------------------------------------------------
// Notes:
// - Fixed-point representation is used for input, slope, and output.
// - The module assumes that the input and slope are provided in
//   signed fixed-point format with DATA_WIDTH bits, where FRAC_WIDTH bits
//   represent the fractional part.
// - The output is also in signed fixed-point format with DATA_WIDTH bits.
// ================================================================================




// ================================================================================
// Module Definition
// ================================================================================
module parametric_relu #(
    parameter DATA_WIDTH = 32,
    parameter FRAC_WIDTH = 16
) (
    input  wire                         clk,
    input  wire                         rst_n,
    input  wire signed [DATA_WIDTH-1:0] in_data,  // Input Data (fixed-point)
    input  wire signed [DATA_WIDTH-1:0] slope,    // Learnable Slope Parameter
    output reg signed  [DATA_WIDTH-1:0] out_data  // Output Data
);

    // ======================================================================
    // PReLU Activation
    // ======================================================================
    reg signed [2*DATA_WIDTH-1:0] product;
    always @(posedge clk or negedge rst_n) begin
        if (!rst_n) begin
            out_data <= 0;
            product  <= 0;
        end else begin
            if (in_data >= 0) begin
                out_data <= in_data;
            end else begin
                product  <= in_data * slope;

                // Adjust for fixed-point scaling
                out_data <= product >>> FRAC_WIDTH;
            end
        end
    end

endmodule

tb/tb_parametric_relu.v
// ================================================================================
// Testbench for Parametric ReLU (PReLU) Module
// ================================================================================

`timescale 1ns / 1ps

// ================================================================================
// Testbench Module Definition
// ================================================================================
module tb_parametric_relu;

    // Parameters
    localparam DATA_WIDTH = 32;
    localparam FRAC_WIDTH = 16;

    localparam ONE = 1 << FRAC_WIDTH;  // Fixed-point representation of 1.0

    // Ports
    reg clk;
    reg rst_n;
    reg [DATA_WIDTH-1:0] in_data;
    reg [DATA_WIDTH-1:0] slope;
    wire [DATA_WIDTH-1:0] out_data;

    // Clock Generation
    initial clk = 0;
    always #5 clk = ~clk;

    parametric_relu #(
        .DATA_WIDTH(DATA_WIDTH),
        .FRAC_WIDTH(FRAC_WIDTH)
    ) prelu_inst (
        .clk(clk),
        .rst_n(rst_n),
        .in_data(in_data),
        .slope(slope),
        .out_data(out_data)
    );

    // ======================================================================
    // Test Vectors
    // ======================================================================
    initial begin

        // File for waveform dump
        $dumpfile("sim/tb_parametric_relu.vcd");
        $dumpvars(0, tb_parametric_relu);

        // Initialize signals
        rst_n   = 0;
        in_data = 0;
        slope   = 1 * ONE;
        #15;
        rst_n = 1;
        #10;
        // Test positive input
        in_data = 2 * ONE;  // 2.0 Output should be 2.0
        #40;
        $display("Input: %0f, Slope: %0f, Output: %0f", $itor(in_data) / ONE, $itor(slope) / ONE,
                 $itor(out_data) / ONE);
        // Test negative input
        in_data = -1 * ONE;  // -1.0 Output should be -1.0 * slope = -1.0
        #40;
        $display("Input: %0f, Slope: %0f, Output: %0f", $itor(in_data) / ONE, $itor(slope) / ONE,
                 $itor(out_data) / ONE);
        // Test zero input
        in_data = 0 * ONE;  // 0.0
        #40;
        $display("Input: %0f, Slope: %0f, Output: %0f", $itor(in_data) / ONE, $itor(slope) / ONE,
                 $itor(out_data) / ONE);
        // Test another negative input with different slope
        slope   = 0.5 * ONE;  // Slope = 0.5 in fixed-point
        in_data = -0.5 * ONE;  // -0.5
        #40;
        $display("Input: %0f, Slope: %0f, Output: %0f", $itor(in_data) / ONE, $itor(slope) / ONE,
                 $itor(out_data) / ONE);
        // Finish simulation
        $finish;
    end

endmodule

sim/tb_parametric_relu.vcd
$date
	Thu Jan 22 15:50:35 2026
$end
$version
	Icarus Verilog
$end
$timescale
	1ps
$end
$scope module tb_parametric_relu $end
$var wire 32 ! out_data [31:0] $end
$var parameter 32 " DATA_WIDTH $end
$var parameter 32 # FRAC_WIDTH $end
$var parameter 48 $ ONE $end
$var reg 1 % clk $end
$var reg 32 & in_data [31:0] $end
$var reg 1 ' rst_n $end
$var reg 32 ( slope [31:0] $end
$scope module prelu_inst $end
$var wire 1 % clk $end
$var wire 32 ) in_data [31:0] $end
$var wire 1 ' rst_n $end
$var wire 32 * slope [31:0] $end
$var parameter 32 + DATA_WIDTH $end
$var parameter 32 , FRAC_WIDTH $end
$var reg 32 - out_data [31:0] $end
$var reg 64 . product [63:0] $end
$upscope $end
$upscope $end
$enddefinitions $end
$comment Show the parameter values. $end
$dumpall
b10000 ,
b100000 +
b10000000000000000 $
b10000 #
b100000 "
$end
#0
$dumpvars
b0 .
b0 -
b10000000000000000 *
b0 )
b10000000000000000 (
0'
b0 &
0%
b0 !
$end
#5000
1%
#10000
0%
#15000
1%
1'
#20000
0%
#25000
b100000000000000000 !
b100000000000000000 -
1%
b100000000000000000 &
b100000000000000000 )
#30000
0%
#35000
1%
#40000
0%
#45000
1%
#50000
0%
#55000
1%
#60000
0%
#65000
b0 !
b0 -
b1111111111111111111111111111111100000000000000000000000000000000 .
1%
b11111111111111110000000000000000 &
b11111111111111110000000000000000 )
#70000
0%
#75000
b11111111111111110000000000000000 !
b11111111111111110000000000000000 -
1%
#80000
0%
#85000
1%
#90000
0%
#95000
1%
#100000
0%
#105000
b0 !
b0 -
1%
b0 &
b0 )
#110000
0%
#115000
1%
#120000
0%
#125000
1%
#130000
0%
#135000
1%
#140000
0%
#145000
b11111111111111110000000000000000 !
b11111111111111110000000000000000 -
b1111111111111111111111111111111111000000000000000000000000000000 .
1%
b11111111111111111000000000000000 &
b11111111111111111000000000000000 )
b1000000000000000 (
b1000000000000000 *
#150000
0%
#155000
b11111111111111111100000000000000 !
b11111111111111111100000000000000 -
1%
